[{"model": "FoodWaste.existingdatasource", "pk": 1, "fields": {"name": "Abstract"}}, {"model": "FoodWaste.existingdatasource", "pk": 2, "fields": {"name": "Book"}}, {"model": "FoodWaste.existingdatasource", "pk": 3, "fields": {"name": "Book Chapter"}}, {"model": "FoodWaste.existingdatasource", "pk": 4, "fields": {"name": "Computer Product"}}, {"model": "FoodWaste.existingdatasource", "pk": 5, "fields": {"name": "Journal Article"}}, {"model": "FoodWaste.existingdatasource", "pk": 6, "fields": {"name": "Manual"}}, {"model": "FoodWaste.existingdatasource", "pk": 7, "fields": {"name": "Presentation"}}, {"model": "FoodWaste.existingdatasource", "pk": 8, "fields": {"name": "Proceedings"}}, {"model": "FoodWaste.existingdatasource", "pk": 9, "fields": {"name": "Report"}}, {"model": "FoodWaste.existingdatasource", "pk": 10, "fields": {"name": "Scientific Data: Datasets"}}, {"model": "FoodWaste.existingdatasource", "pk": 11, "fields": {"name": "Other"}}]